{
	"configurations" : 
	[
		{
			"directories" : 
			[
				{
					"build" : ".",
					"jsonFile" : "directory-.-Debug-d0094a50bb2071803777.json",
					"minimumCMakeVersion" : 
					{
						"string" : "3.5"
					},
					"projectIndex" : 0,
					"source" : ".",
					"targetIndexes" : 
					[
						0,
						1
					]
				}
			],
			"name" : "Debug",
			"projects" : 
			[
				{
					"directoryIndexes" : 
					[
						0
					],
					"name" : "display_a_scene",
					"targetIndexes" : 
					[
						0,
						1
					]
				}
			],
			"targets" : 
			[
				{
					"directoryIndex" : 0,
					"id" : "display_a_scene::@6890427a1f51a3e7e1df",
					"jsonFile" : "target-display_a_scene-Debug-f07b54473b1b2364d7fd.json",
					"name" : "display_a_scene",
					"projectIndex" : 0
				},
				{
					"directoryIndex" : 0,
					"id" : "display_a_scene_autogen::@6890427a1f51a3e7e1df",
					"jsonFile" : "target-display_a_scene_autogen-Debug-52bfc5153c99f85b3944.json",
					"name" : "display_a_scene_autogen",
					"projectIndex" : 0
				}
			]
		}
	],
	"kind" : "codemodel",
	"paths" : 
	{
		"build" : "C:/Users/HAL/Documents/display_a_scene/cmake-build-debug-visual-studio",
		"source" : "C:/Users/HAL/Documents/display_a_scene"
	},
	"version" : 
	{
		"major" : 2,
		"minor" : 3
	}
}
